main.py
app_maker_mcp-0.0.3.dist-info/METADATA
app_maker_mcp-0.0.3.dist-info/WHEEL
app_maker_mcp-0.0.3.dist-info/entry_points.txt
app_maker_mcp-0.0.3.dist-info/top_level.txt
app_maker_mcp-0.0.3.dist-info/RECORD
