Metadata-Version: 2.4
Name: app-maker-mcp
Version: 0.0.3
Summary: Create and serve web applications that can use goose, quickly
Author: Michael Neale
License: MIT
Project-URL: Homepage, https://github.com/michaelneale/
Requires-Python: >=3.12
Requires-Dist: mcp[cli]>=1.3.0
Requires-Dist: requests>=2.31.0
